agentscape/__init__.py
agentscape/__main__.py
agentscape/project.py
agentscape/agents/__init__.py
agentscape/agents/agent.py
agentscape/agents/triage_agent.py
agentscape/agents/weather_agent.py
agentscape-0.1.1.dist-info/METADATA
agentscape-0.1.1.dist-info/WHEEL
agentscape-0.1.1.dist-info/entry_points.txt
agentscape-0.1.1.dist-info/top_level.txt
agentscape-0.1.1.dist-info/RECORD
